Blackprint/Engine.py
Blackprint/Environment.py
Blackprint/Event.py
Blackprint/Interface.py
Blackprint/Internal.py
Blackprint/Node.py
Blackprint/PortGhost.py
Blackprint/RoutePort.py
Blackprint/Types.py
Blackprint/Utils.py
Blackprint/__init__.py
Blackprint/Constructor/Cable.py
Blackprint/Constructor/CustomEvent.py
Blackprint/Constructor/InstanceEvent.py
Blackprint/Constructor/OrderedExecution.py
Blackprint/Constructor/Port.py
Blackprint/Constructor/PortLink.py
Blackprint/Constructor/References.py
Blackprint/Nodes/BPEvent.py
Blackprint/Nodes/BPFunction.py
Blackprint/Nodes/BPVariable.py
Blackprint/Nodes/BPVariable_init.py
Blackprint/Nodes/Enums.py
Blackprint/Nodes/Environments.py
Blackprint/Nodes/FnPortVar.py
Blackprint/Port/PortFeature.py
blackprint_engine-0.9.0.dist-info/LICENSE
blackprint_engine-0.9.0.dist-info/METADATA
blackprint_engine-0.9.0.dist-info/WHEEL
blackprint_engine-0.9.0.dist-info/top_level.txt
blackprint_engine-0.9.0.dist-info/RECORD
