Metadata-Version: 2.1
Name: blackprint-engine
Version: 0.9.0
Summary: Blackprint engine for registering node/interface and run exported Blackprint on Python environment
Home-page: https://github.com/Blackprint/engine-python
License: LICENSE
Project-URL: Homepage, https://github.com/Blackprint/engine-python
Project-URL: Bug Tracker, https://github.com/Blackprint/engine-python/issues
Classifier: Programming Language :: Python :: 3
Classifier: License :: OSI Approved :: MIT License
Classifier: Development Status :: 4 - Beta
Requires-Python: >=3.10
License-File: LICENSE
